mdatpy/__init__.py
mdatpy/bin/__init__.py
mdatpy/bin/cp_landmark_files.py
mdatpy/bin/dataset.py
mdatpy/bin/datasets/__init__.py
mdatpy/bin/datasets/basic_dataset.py
mdatpy/bin/datasets/dataset_base.py
mdatpy/bin/datasets/debug_image_dataset.py
mdatpy/bin/datasets/graph_dataset.py
mdatpy/bin/datasets/pyro_dataset.py
mdatpy/bin/datasets/reference_image_transformation_dataset.py
mdatpy/bin/datasources/__init__.py
mdatpy/bin/datasources/cached_image_datasource.py
mdatpy/bin/datasources/datasource_base.py
mdatpy/bin/datasources/image_datasource.py
mdatpy/bin/datasources/json_datasource.py
mdatpy/bin/datasources/label_datasource.py
mdatpy/bin/datasources/landmark_datasource.py
mdatpy/bin/datasources/video_frame_list_datasource.py
mdatpy/bin/generators/__init__.py
mdatpy/bin/generators/generator_base.py
mdatpy/bin/generators/image_generator.py
mdatpy/bin/generators/image_size_generator.py
mdatpy/bin/generators/label_generator.py
mdatpy/bin/generators/landmark_generator.py
mdatpy/bin/generators/transformation_generator_base.py
mdatpy/bin/generators/video_frame_list_generator.py
mdatpy/bin/graph/__init__.py
mdatpy/bin/graph/node.py
mdatpy/bin/graph/run_graph.py
mdatpy/bin/im_split.py
mdatpy/bin/iterators/__init__.py
mdatpy/bin/iterators/id_list_iterator.py
mdatpy/bin/iterators/id_list_iterator_base.py
mdatpy/bin/iterators/iterator_base.py
mdatpy/bin/iterators/resample_labels_id_list_iterator.py
mdatpy/bin/iterators/video_frame_id_list_iterator.py
mdatpy/bin/main_spine_localization.py
mdatpy/bin/main_vertebrae_localization.py
mdatpy/bin/network.py
mdatpy/bin/possible_successors.pickle
mdatpy/bin/preprocess.py
mdatpy/bin/spine_localization_postprocessing.py
mdatpy/bin/start_cv.py
mdatpy/bin/tensorflow_train/__init__.py
mdatpy/bin/tensorflow_train/data_generator.py
mdatpy/bin/tensorflow_train/data_generator_base.py
mdatpy/bin/tensorflow_train/data_generator_padding.py
mdatpy/bin/tensorflow_train/layers/__init__.py
mdatpy/bin/tensorflow_train/layers/conv_lstm.py
mdatpy-0.0.4.dist-info/LICENSE
mdatpy-0.0.4.dist-info/WHEEL
mdatpy-0.0.4.dist-info/METADATA
mdatpy-0.0.4.dist-info/RECORD
