Metadata-Version: 2.1
Name: mdatpy
Version: 0.0.4
Summary: A pypi release of the MDAT
Home-page: https://github.com/a-parida12/MDAT
License: MIT
Author: Abhijeet Parida
Author-email: abhijeet.parida@tum.de
Requires-Python: >=3.10.0,<3.11.0
Classifier: License :: OSI Approved :: MIT License
Classifier: Programming Language :: Python :: 3
Classifier: Programming Language :: Python :: 3.10
Requires-Dist: SimpleITK (>=2.2.0,<3.0.0)
Requires-Dist: itk (==5.3rc4)
Requires-Dist: matplotlib (>=3.6.0,<4.0.0)
Requires-Dist: networkx (>=2.8.7,<3.0.0)
Requires-Dist: scikit-image (>=0.19.3,<0.20.0)
Requires-Dist: tensorflow (>=2.10.0,<3.0.0)
Requires-Dist: tensorflow-gpu (>=2.10.0,<3.0.0)
Project-URL: Repository, https://github.com/a-parida12/MDAT
